Lynx/__init__.py
Lynx/modules/__init__.py
Lynx/modules/compare.py
Lynx/modules/generate.py
Lynx/modules/init.py
Lynx/templates/generator.py
Lynx/templates/cpp/problem.yaml
Lynx/templates/cpp/problem_zh.md
Lynx/templates/cpp/additional_file/.gitkeep
Lynx/templates/cpp/programs/checker.cpp
Lynx/templates/cpp/programs/std.cpp
Lynx/templates/cpp/programs/validator.cpp
Lynx/templates/cpp/testdata/config.yaml
Lynx/utils/__init__.py
Lynx/utils/config.py
Lynx/utils/constants.py
Lynx/utils/log.py
Lynx/utils/language/__init__.py
Lynx/utils/language/cpp.py
testlib/.git
testlib/.gitattributes
testlib/.gitignore
testlib/LICENSE
testlib/README.md
testlib/read.me
testlib/testlib.h
testlib/checkers/.gitignore
testlib/checkers/acmp.cpp
testlib/checkers/caseicmp.cpp
testlib/checkers/casencmp.cpp
testlib/checkers/casewcmp.cpp
testlib/checkers/dcmp.cpp
testlib/checkers/fcmp.cpp
testlib/checkers/hcmp.cpp
testlib/checkers/icmp.cpp
testlib/checkers/lcmp.cpp
testlib/checkers/ncmp.cpp
testlib/checkers/nyesno.cpp
testlib/checkers/pointscmp.cpp
testlib/checkers/pointsinfo.cpp
testlib/checkers/rcmp.cpp
testlib/checkers/rcmp4.cpp
testlib/checkers/rcmp6.cpp
testlib/checkers/rcmp9.cpp
testlib/checkers/rncmp.cpp
testlib/checkers/uncmp.cpp
testlib/checkers/wcmp.cpp
testlib/checkers/yesno.cpp
testlib/validators/bipartite-graph-validator.cpp
testlib/validators/case-nval.cpp
testlib/validators/ival.cpp
testlib/validators/nval.cpp
testlib/validators/sval.cpp
testlib/validators/undirected-graph-validator.cpp
testlib/validators/undirected-tree-validator.cpp
testlib/validators/validate-using-testset-and-group.cpp
pyLynx-2.0.1b4.dist-info/LICENSE
pyLynx-2.0.1b4.dist-info/METADATA
pyLynx-2.0.1b4.dist-info/WHEEL
pyLynx-2.0.1b4.dist-info/entry_points.txt
pyLynx-2.0.1b4.dist-info/top_level.txt
pyLynx-2.0.1b4.dist-info/RECORD
